textmate_grammar/__init__.py
textmate_grammar/elements.py
textmate_grammar/handler.py
textmate_grammar/parser.py
textmate_grammar/parsers/__init__.py
textmate_grammar/parsers/base.py
textmate_grammar/parsers/markdown/LICENSE.txt
textmate_grammar/parsers/markdown/__init__.py
textmate_grammar/parsers/markdown/grammar.yaml
textmate_grammar/parsers/matlab/__init__.py
textmate_grammar/parsers/matlab/grammar.yaml
textmate_grammar/parsers/matlab/license.txt
textmate_grammar/py.typed
textmate_grammar/utils/__init__.py
textmate_grammar/utils/cache.py
textmate_grammar/utils/exceptions.py
textmate_grammar/utils/logger.py
textmate_grammar_python-0.6.1.dist-info/LICENSE
textmate_grammar_python-0.6.1.dist-info/METADATA
textmate_grammar_python-0.6.1.dist-info/WHEEL
textmate_grammar_python-0.6.1.dist-info/RECORD
