Metadata-Version: 2.1
Name: textmate-grammar-python
Version: 0.6.1
Summary: A lexer and tokenizer for grammar files as defined by TextMate and used in VSCode, implemented in Python.
Home-page: https://github.com/watermarkhu/textmate-grammar-python
License: MIT
Keywords: textmate,tokenization
Author: Mark Shui Hu
Author-email: watermarkhu@gmail.com
Requires-Python: >=3.9,<4.0
Classifier: License :: OSI Approved :: MIT License
Classifier: Programming Language :: Python :: 3
Classifier: Programming Language :: Python :: 3.9
Classifier: Programming Language :: Python :: 3.10
Classifier: Programming Language :: Python :: 3.11
Classifier: Programming Language :: Python :: 3.12
Requires-Dist: PyYAML (>=6.0.1,<7.0.0)
Requires-Dist: charset-normalizer (>=3.3.2,<4.0.0)
Requires-Dist: onigurumacffi (>=1.3.0,<2.0.0)
Project-URL: Documentation, https://textmate-grammar-python.readthedocs.io
Project-URL: Repository, https://github.com/watermarkhu/textmate-grammar-python
